binary_to_gray.v
module binary_to_gray(
    input [3:0] B,
    output [3:0] G
    );
	 assign G[3]=B[3];
	 xor(G[2],B[3],B[2]);
	 xor(G[1],B[2],B[1]);
	 xor(G[0],B[1],B[0]);


endmodule

binary_to_gray_tb.v
//`include "binary_to_gray.v"
module binary_to_gray_tb;

	// Inputs
	reg [3:0] B;

	// Outputs
	wire [3:0] G;

	// Instantiate the Unit Under Test (UUT)
	binary_to_gray uut (
		.B(B), 
		.G(G)
	);

	initial begin
		
$dumpfile("binary_to_gray.vcd");
$dumpvars(0, uut);
		$monitor($time,"B=%h,G=%h",B,G);
		B=4'h0;
	#5	B=4'h1;
	#5	B=4'h2;
	#5	B=4'h3;
	#5	B=4'h4;
	#5	B=4'h5;
	#5	B=4'h6;
	#5	B=4'h7;
	#5	B=4'h8;
	#5	B=4'h9;
	#5	B=4'ha;
	#5	B=4'hb;
	#5	B=4'hc;
	#5	B=4'hd;
	#5	B=4'he;
	#5	B=4'hf;
	#5 $finish;
      
    end
  
endmodule

binary_to_gray.vcd
$date
	Tue Jan 10 09:56:01 2023
$end
$version
	Icarus Verilog
$end
$timescale
	1s
$end
$scope module binary_to_gray_tb $end
$scope module uut $end
$var wire 4 ! B [3:0] $end
$var wire 4 " G [3:0] $end
$upscope $end
$upscope $end
$enddefinitions $end
#0
$dumpvars
b0 "
b0 !
$end
#5
b1 "
b1 !
#10
b11 "
b10 !
#15
b10 "
b11 !
#20
b110 "
b100 !
#25
b111 "
b101 !
#30
b101 "
b110 !
#35
b100 "
b111 !
#40
b1100 "
b1000 !
#45
b1101 "
b1001 !
#50
b1111 "
b1010 !
#55
b1110 "
b1011 !
#60
b1010 "
b1100 !
#65
b1011 "
b1101 !
#70
b1001 "
b1110 !
#75
b1000 "
b1111 !
